config.yaml
data/base_items_validation.json
data/extracted_mod_stats.json
data/extracted_passive_stats.json
data/fresh_active_skills.json
data/fresh_complete_skill_data.json
data/fresh_damage_patterns.json
data/fresh_data_auto_parsed.json
data/fresh_dec12_extraction.json
data/fresh_extracted_damages.json
data/fresh_perlevel_analysis.json
data/fresh_skill_data.json
data/fresh_skills_dec12.json
data/merged_passive_tree.json
data/modfamily_extracted.json
data/passive_stats_binary.json
data/passive_tree_positions.json
data/passive_tree_validation_results.json
data/passiveskills_to_pob_mapping.json
data/pob_active_skills.json
data/pob_active_skills_backup.json
data/pob_active_skills_backup_v2.json
data/pob_active_skills_enhanced.json
data/pob_active_skills_enhanced_v2.json
data/pob_active_skills_original.json
data/pob_complete_skills.json
data/pob_level1_damages.json
data/pob_passive_nodes.json
data/pob_skill_stats.json
data/pob_to_datc64_mapping.json
data/pob_to_passiveskills_mapping.json
data/pob_to_passiveskills_mapping_v2.json
data/poe2_mods_corrected.json
data/poe2_mods_extracted.json
data/poe2_skill_damage_analysis.json
data/poe2_spell_gems_database.json
data/poe2_stats_complete.json
data/poe2_support_gems_database.json
data/poe2_support_gems_database_backup.json
data/psg_passive_nodes.json
data/reverse_engineered_spec.json
data/spirit_costs.json
data/stats_sample.json
poe2_mcp-1.0.0.dist-info/licenses/LICENSE
src/__init__.py
src/config.py
src/mcp_server.py
src/ai/__init__.py
src/ai/query_handler.py
src/ai/recommendation_engine.py
src/analyzer/archetype_classifier.py
src/analyzer/build_success_predictor.py
src/analyzer/character_analyzer.py
src/analyzer/character_comparator.py
src/analyzer/content_readiness_checker.py
src/analyzer/damage_scaling_analyzer.py
src/analyzer/gear_comparator.py
src/analyzer/gear_evaluator.py
src/analyzer/report_generator.py
src/analyzer/top_player_fetcher.py
src/analyzer/weakness_detector.py
src/api/__init__.py
src/api/cache_manager.py
src/api/character_fetcher.py
poe2_mcp-1.0.0.dist-info/METADATA
poe2_mcp-1.0.0.dist-info/WHEEL
poe2_mcp-1.0.0.dist-info/entry_points.txt
poe2_mcp-1.0.0.dist-info/top_level.txt
poe2_mcp-1.0.0.dist-info/RECORD
