Metadata-Version: 2.4
Name: poe2-mcp
Version: 1.0.0
Summary: AI-powered Path of Exile 2 build optimization MCP server
Author-email: HivemindOverlord <connor@portertech.llc>
License: MIT
Project-URL: Homepage, https://github.com/HivemindOverlord/poe2-mcp
Project-URL: Repository, https://github.com/HivemindOverlord/poe2-mcp
Project-URL: Issues, https://github.com/HivemindOverlord/poe2-mcp/issues
Project-URL: Changelog, https://github.com/HivemindOverlord/poe2-mcp/blob/main/CHANGELOG.md
Keywords: path-of-exile,poe2,mcp,model-context-protocol,ai,build-optimizer,gaming
Classifier: Development Status :: 4 - Beta
Classifier: Intended Audience :: Developers
Classifier: Intended Audience :: End Users/Desktop
Classifier: License :: OSI Approved :: MIT License
Classifier: Operating System :: OS Independent
Classifier: Programming Language :: Python :: 3
Classifier: Programming Language :: Python :: 3.9
Classifier: Programming Language :: Python :: 3.10
Classifier: Programming Language :: Python :: 3.11
Classifier: Programming Language :: Python :: 3.12
Classifier: Programming Language :: Python :: 3.13
Classifier: Topic :: Games/Entertainment
Classifier: Topic :: Scientific/Engineering :: Artificial Intelligence
Requires-Python: >=3.9
License-File: LICENSE
Requires-Dist: mcp>=0.9.0
Requires-Dist: fastapi>=0.104.0
Requires-Dist: uvicorn[standard]>=0.24.0
Requires-Dist: pydantic>=2.5.0
Requires-Dist: pydantic-settings>=2.1.0
Requires-Dist: sqlalchemy>=2.0.0
Requires-Dist: alembic>=1.12.0
Requires-Dist: aiosqlite>=0.19.0
Requires-Dist: httpx>=0.25.0
Requires-Dist: aiohttp>=3.9.0
Requires-Dist: requests>=2.31.0
Requires-Dist: anthropic>=0.8.0
Requires-Dist: beautifulsoup4>=4.12.0
Requires-Dist: lxml>=4.9.3
Requires-Dist: python-dotenv>=1.0.0
Requires-Dist: pyyaml>=6.0.1
Requires-Dist: loguru>=0.7.2
Requires-Dist: tenacity>=8.2.3
Requires-Dist: cachetools>=5.3.2
Requires-Dist: ratelimit>=2.2.1
Requires-Dist: slowapi>=0.1.9
Requires-Dist: python-dateutil>=2.8.2
Requires-Dist: pytz>=2023.3
Requires-Dist: xmltodict>=0.13.0
Requires-Dist: defusedxml>=0.7.1
Requires-Dist: validators>=0.22.0
Requires-Dist: email-validator>=2.1.0
Requires-Dist: aiofiles>=23.2.1
Requires-Dist: orjson>=3.9.10
Requires-Dist: jinja2>=3.1.2
Requires-Dist: python-multipart>=0.0.6
Provides-Extra: trade
Requires-Dist: playwright>=1.40.0; extra == "trade"
Provides-Extra: dev
Requires-Dist: pytest>=7.4.0; extra == "dev"
Requires-Dist: pytest-asyncio>=0.21.0; extra == "dev"
Requires-Dist: pytest-cov>=4.1.0; extra == "dev"
Requires-Dist: pytest-mock>=3.12.0; extra == "dev"
Requires-Dist: black>=23.11.0; extra == "dev"
Requires-Dist: flake8>=6.1.0; extra == "dev"
Requires-Dist: mypy>=1.7.0; extra == "dev"
Requires-Dist: isort>=5.12.0; extra == "dev"
Provides-Extra: all
Requires-Dist: poe2-mcp[dev,trade]; extra == "all"
Dynamic: license-file
